ddxl/__init__.py
ddxl/container/__init__.py
ddxl/container/container.py
ddxl/container/errors.py
ddxl/container/status.py
ddxl/manager/__init__.py
ddxl/manager/errors.py
ddxl/manager/manager.py
ddxl-0.0.7.dist-info/LICENSE
ddxl-0.0.7.dist-info/METADATA
ddxl-0.0.7.dist-info/WHEEL
ddxl-0.0.7.dist-info/top_level.txt
ddxl-0.0.7.dist-info/RECORD
